steam_tools_ng/__init__.py
steam_tools_ng/__main__.py
steam_tools_ng/cli.py
steam_tools_ng/config.py
steam_tools_ng/gui.py
steam_tools_ng/i18n.py
steam_tools_ng/logger_handlers.py
steam_tools_ng/py.typed
steam_tools_ng/console/__init__.py
steam_tools_ng/console/authenticator.py
steam_tools_ng/console/cli.py
steam_tools_ng/console/login.py
steam_tools_ng/console/utils.py
steam_tools_ng/core/__init__.py
steam_tools_ng/core/cardfarming.py
steam_tools_ng/core/confirmations.py
steam_tools_ng/core/coupons.py
steam_tools_ng/core/fakerun.py
steam_tools_ng/core/market.py
steam_tools_ng/core/steamgifts.py
steam_tools_ng/core/steamguard.py
steam_tools_ng/core/steamtrades.py
steam_tools_ng/core/utils.py
steam_tools_ng/gtk/__init__.py
steam_tools_ng/gtk/about.py
steam_tools_ng/gtk/application.py
steam_tools_ng/gtk/async_gtk.py
steam_tools_ng/gtk/authenticator.py
steam_tools_ng/gtk/confirmation.py
steam_tools_ng/gtk/coupon.py
steam_tools_ng/gtk/login.py
steam_tools_ng/gtk/market.py
steam_tools_ng/gtk/settings.py
steam_tools_ng/gtk/update.py
steam_tools_ng/gtk/utils.py
steam_tools_ng/gtk/window.py
steam_tools_ng/icons/stng.ico
steam_tools_ng/icons/stng.png
steam_tools_ng/icons/stng_console.ico
steam_tools_ng/icons/stng_console.png
steam_tools_ng/icons/stng_nc.ico
steam_tools_ng/icons/stng_nc.png
steam_tools_ng-4.0.dist-info/LICENSE
steam_tools_ng-4.0.dist-info/METADATA
steam_tools_ng-4.0.dist-info/WHEEL
steam_tools_ng-4.0.dist-info/entry_points.txt
steam_tools_ng-4.0.dist-info/top_level.txt
steam_tools_ng-4.0.dist-info/RECORD
