Metadata-Version: 2.1
Name: steam-tools-ng
Version: 4.0
Summary: Steam Tools NG
Author: Lara Maia
Author-email: dev@lara.monster
License: GPLv3
Project-URL: homepage, https://github.com/calendulish/steam-tools-ng
Project-URL: repository, https://github.com
Project-URL: changelog, https://github.com/calendulish/steam-tools-ng/releases
Keywords: steam,valve
Classifier: Development Status :: 4 - Beta
Classifier: Intended Audience :: End Users/Desktop
Classifier: Topic :: Games/Entertainment
Classifier: License :: OSI Approved :: GNU General Public License v3 (GPLv3)
Classifier: Operating System :: POSIX :: Linux
Classifier: Operating System :: Microsoft :: Windows :: Windows 10
Classifier: Environment :: X11 Applications :: GTK
Classifier: Programming Language :: Python :: 3 :: Only
Classifier: Programming Language :: Python :: 3.9
Classifier: Programming Language :: Python :: 3.10
Classifier: Programming Language :: Python :: 3.11
Classifier: Programming Language :: Python :: 3.12
Classifier: Typing :: Typed
Requires-Python: >=3.10
License-File: LICENSE
Requires-Dist: stlib~=2.3
Requires-Dist: stlib-plugins~=1.2
Requires-Dist: aiohttp
Requires-Dist: certifi
Requires-Dist: pywin32; sys_platform == "win32"
